stocknflow
