Metadata-Version: 2.1
Name: stocknflow
Version: 0.0.9
Summary: Stocks and flows maps
Home-page: https://gitlab.com/mrteste/stocknflow
Author: Julien Jamme
Author-email: julien.jamme@protonmail.com
Maintainer: Julien Jamme
License: GPL3
Keywords: map stocks proportionnal circles flows
Platform: UNKNOWN
Classifier: Development Status :: 4 - Beta
Classifier: Programming Language :: Python :: 3
Classifier: License :: OSI Approved :: GNU General Public License v3 (GPLv3)
Classifier: Operating System :: OS Independent
